tno/fl/protocols/logistic_regression/__init__.py
tno/fl/protocols/logistic_regression/client.py
tno/fl/protocols/logistic_regression/msg_ids.py
tno/fl/protocols/logistic_regression/py.typed
tno/fl/protocols/logistic_regression/server.py
tno/fl/protocols/logistic_regression/test/__init__.py
tno/fl/protocols/logistic_regression/test/test_protocol.py
tno/fl/protocols/logistic_regression/test/test_statistics.py
tno.fl.protocols.logistic_regression-1.1.0.dist-info/LICENSE
tno.fl.protocols.logistic_regression-1.1.0.dist-info/METADATA
tno.fl.protocols.logistic_regression-1.1.0.dist-info/WHEEL
tno.fl.protocols.logistic_regression-1.1.0.dist-info/top_level.txt
tno.fl.protocols.logistic_regression-1.1.0.dist-info/RECORD
