Metadata-Version: 2.1
Name: tno.fl.protocols.logistic_regression
Version: 1.1.0
Summary: Implementation of a Federated Learning scheme for Logistic Regression
Author-email: TNO PET Lab <petlab@tno.nl>
Maintainer-email: TNO PET Lab <petlab@tno.nl>
License: Apache License, Version 2.0
Project-URL: Homepage, https://pet.tno.nl/
Project-URL: Documentation, https://docs.pet.tno.nl/fl/protocols/logistic_regression/1.1.0
Project-URL: Source, https://github.com/TNO-FL/protocols.logistic_regression
Keywords: TNO,FL,federated learning,machine learning,logistic regression
Platform: any
Classifier: License :: OSI Approved :: Apache Software License
Classifier: Programming Language :: Python :: 3
Classifier: Operating System :: OS Independent
Classifier: Intended Audience :: Developers
Classifier: Intended Audience :: Information Technology
Classifier: Intended Audience :: Science/Research
Classifier: Typing :: Typed
Requires-Python: >=3.9
License-File: LICENSE
Requires-Dist: numpy<3,>=1.17
Requires-Dist: pandas<3.0,>=1.0
Requires-Dist: tno.mpc.communication~=4.8
Requires-Dist: scipy>=1.10
Provides-Extra: tests
Requires-Dist: pandas-stubs; extra == "tests"
Requires-Dist: pytest>=8.1; extra == "tests"
Requires-Dist: pytest-asyncio~=0.21.0; extra == "tests"
